caffi/__init__.py
caffi/_ca.py
caffi/_version.py
caffi/ca.py
caffi/compat.py
caffi/constants.py
caffi/dbr.py
caffi/macros.py
caffi/lib/darwin-aarch64/libCom.dylib
caffi/lib/darwin-aarch64/libca.dylib
caffi/lib/darwin-x86/libCom.dylib
caffi/lib/darwin-x86/libca.dylib
caffi/lib/linux-x86/libCom.so
caffi/lib/linux-x86/libca.so
caffi/lib/linux-x86_64/libCom.so
caffi/lib/linux-x86_64/libca.so
caffi/lib/win32-x86/Com.dll
caffi/lib/win32-x86/ca.dll
caffi/lib/windows-x64/Com.dll
caffi/lib/windows-x64/ca.dll
caffi-1.0.4.dist-info/LICENSE
caffi-1.0.4.dist-info/METADATA
caffi-1.0.4.dist-info/WHEEL
caffi-1.0.4.dist-info/top_level.txt
caffi-1.0.4.dist-info/RECORD
