Metadata-Version: 2.1
Name: caffi
Version: 1.0.4
Summary: Channel Access Foreign Function Interface
Home-page: https://github.com/CaChannel/caffi
Author: Xiaoqiang Wang
Author-email: xiaoqiang.wang@psi.ch
License: BSD
Platform: Windows
Platform: Linux
Platform: Mac OS X
Classifier: Development Status :: 4 - Beta
Classifier: Environment :: Console
Classifier: Intended Audience :: Developers
Classifier: License :: OSI Approved :: BSD License
Classifier: Programming Language :: Python :: 2
Classifier: Programming Language :: Python :: 3
License-File: LICENSE
Requires-Dist: cffi >=1.3.0
